quantrs2-0.1.0a5.dist-info/METADATA
quantrs2-0.1.0a5.dist-info/WHEEL
quantrs2/__init__.py
quantrs2/__pycache__/__init__.cpython-310.pyc
quantrs2/__pycache__/__init__.cpython-312.pyc
quantrs2/__pycache__/__init__.cpython-313.pyc
quantrs2/__pycache__/advanced_algorithms.cpython-312.pyc
quantrs2/__pycache__/advanced_algorithms.cpython-313.pyc
quantrs2/__pycache__/algorithm_debugger.cpython-310.pyc
quantrs2/__pycache__/algorithm_debugger.cpython-312.pyc
quantrs2/__pycache__/algorithm_debugger.cpython-313.pyc
quantrs2/__pycache__/algorithm_marketplace.cpython-310.pyc
quantrs2/__pycache__/algorithm_marketplace.cpython-312.pyc
quantrs2/__pycache__/algorithm_marketplace.cpython-313.pyc
quantrs2/__pycache__/anneal.cpython-310.pyc
quantrs2/__pycache__/anneal.cpython-312.pyc
quantrs2/__pycache__/anneal.cpython-313.pyc
quantrs2/__pycache__/bell_state.cpython-310.pyc
quantrs2/__pycache__/bell_state.cpython-312.pyc
quantrs2/__pycache__/bell_state.cpython-313.pyc
quantrs2/__pycache__/circuit_builder.cpython-310.pyc
quantrs2/__pycache__/circuit_builder.cpython-312.pyc
quantrs2/__pycache__/circuit_builder.cpython-313.pyc
quantrs2/__pycache__/circuit_db.cpython-310.pyc
quantrs2/__pycache__/circuit_db.cpython-312.pyc
quantrs2/__pycache__/circuit_db.cpython-313.pyc
quantrs2/__pycache__/circuit_optimization_cache.cpython-312.pyc
quantrs2/__pycache__/circuit_optimization_cache.cpython-313.pyc
quantrs2/__pycache__/cirq_integration.cpython-313.pyc
quantrs2/__pycache__/compilation_service.cpython-310.pyc
quantrs2/__pycache__/compilation_service.cpython-312.pyc
quantrs2/__pycache__/compilation_service.cpython-313.pyc
quantrs2/__pycache__/config_management.cpython-312.pyc
quantrs2/__pycache__/config_management.cpython-313.pyc
quantrs2/__pycache__/connection_pooling.cpython-312.pyc
quantrs2/__pycache__/connection_pooling.cpython-313.pyc
quantrs2/__pycache__/core.cpython-313.pyc
quantrs2/__pycache__/crypto.cpython-310.pyc
quantrs2/__pycache__/crypto.cpython-312.pyc
quantrs2/__pycache__/crypto.cpython-313.pyc
quantrs2-0.1.0a5.dist-info/RECORD
