Metadata-Version: 2.4
Name: quantrs2
Version: 0.1.0a5
Classifier: Development Status :: 3 - Alpha
Classifier: Programming Language :: Python :: 3
Classifier: Programming Language :: Python :: 3.8
Classifier: Programming Language :: Python :: 3.9
Classifier: Programming Language :: Python :: 3.10
Classifier: Programming Language :: Python :: 3.11
Classifier: Programming Language :: Python :: 3.12
Classifier: Programming Language :: Rust
Classifier: Topic :: Scientific/Engineering :: Physics
Classifier: Topic :: Scientific/Engineering :: Mathematics
Classifier: Topic :: Scientific/Engineering :: Artificial Intelligence
Classifier: Topic :: Software Development :: Libraries :: Python Modules
Classifier: Intended Audience :: Science/Research
Classifier: Intended Audience :: Developers
Classifier: License :: OSI Approved :: MIT License
Classifier: License :: OSI Approved :: Apache Software License
Requires-Dist: numpy>=1.20.0
Requires-Dist: matplotlib>=3.3.0
Requires-Dist: ipython>=7.0.0
Requires-Dist: psutil>=5.8.0
Requires-Dist: pytest>=6.0.0 ; extra == 'dev'
Requires-Dist: pytest-asyncio>=0.21.0 ; extra == 'dev'
Requires-Dist: pytest-mock>=3.10.0 ; extra == 'dev'
Requires-Dist: pyyaml>=6.0 ; extra == 'dev'
Requires-Dist: black>=22.3.0 ; extra == 'dev'
Requires-Dist: flake8>=5.0.0 ; extra == 'dev'
Requires-Dist: isort>=5.10.0 ; extra == 'dev'
Requires-Dist: requests>=2.28.0 ; extra == 'dev'
Requires-Dist: redis>=4.0.0 ; extra == 'dev'
Requires-Dist: psycopg2-binary>=2.9.0 ; extra == 'dev'
Requires-Dist: cryptography>=40.0.0 ; extra == 'dev'
Requires-Dist: sqlalchemy>=2.0.0 ; extra == 'dev'
Requires-Dist: prometheus-client>=0.16.0 ; extra == 'dev'
Requires-Dist: scikit-learn>=1.0.0 ; extra == 'ml'
Requires-Dist: scipy>=1.7.0 ; extra == 'ml'
Requires-Dist: tabulate>=0.8.0 ; extra == 'gpu'
Provides-Extra: dev
Provides-Extra: ml
Provides-Extra: gpu
Summary: High-performance quantum computing framework with ML, error mitigation, and annealing capabilities
Keywords: quantum,computing,simulator,annealing,gate
Author: QuantRS2 Contributors
Author-email: "QuantRS2 Contributors (Team KitaSan) " <info@kitasan.io>
License: MIT/Apache-2.0
Requires-Python: >=3.8
Project-URL: Homepage, https://github.com/cool-japan/quantrs
Project-URL: Repository, https://github.com/cool-japan/quantrs
Project-URL: Documentation, https://pypi.org/project/quantrs2/
